SOSPysp
