Metadata-Version: 2.1
Name: SOSPysp
Version: 0.1.8
Summary: Python version of MATLAB SOSTOOLS, a toolbox for sum-of-squares optimization
Home-page: https://github.com/zm2404/SOSPy
Author: Zhe Mo
Author-email: zm2404@columbia.edu
Keywords: Sum of Square Optimization,SOSTOOLS
Classifier: Development Status :: 4 - Beta
Classifier: Intended Audience :: Science/Research
Classifier: License :: OSI Approved :: GNU General Public License v3 (GPLv3)
Classifier: Programming Language :: Python :: 3.10
Requires-Python: >=3.10
